LICENSE
setup.py
pacote_python_coupa/converter_xlsx_para_csv.py
pacote_python_coupa/gerar_csv.py
pacote_python_coupa/get_api.py
pacote_python_coupa/pegar_salvar_arquivo.py
pacote_python_coupa.egg-info/PKG-INFO
pacote_python_coupa.egg-info/SOURCES.txt
pacote_python_coupa.egg-info/dependency_links.txt
pacote_python_coupa.egg-info/requires.txt
pacote_python_coupa.egg-info/top_level.txt